hanzo_tools/__init__.py
hanzo_tools/database/__init__.py
hanzo_tools/database/database_manager.py
hanzo_tools/database/graph.py
hanzo_tools/database/graph_add.py
hanzo_tools/database/graph_query.py
hanzo_tools/database/graph_remove.py
hanzo_tools/database/graph_search.py
hanzo_tools/database/graph_stats.py
hanzo_tools/database/sql.py
hanzo_tools/database/sql_query.py
hanzo_tools/database/sql_search.py
hanzo_tools/database/sql_stats.py
hanzo_tools_database-0.2.0.dist-info/METADATA
hanzo_tools_database-0.2.0.dist-info/WHEEL
hanzo_tools_database-0.2.0.dist-info/entry_points.txt
hanzo_tools_database-0.2.0.dist-info/top_level.txt
hanzo_tools_database-0.2.0.dist-info/RECORD
